<?xml version="1.0" encoding="utf-8"?>
<doctrine-mapping xmlns="http://doctrine-project.org/schemas/orm/doctrine-mapping" xmlns:xsi="http://www.w3.org/2001/XMLSchema-instance" xsi:schemaLocation="http://doctrine-project.org/schemas/orm/doctrine-mapping http://doctrine-project.org/schemas/orm/doctrine-mapping.xsd">
  <entity name="Vest\ResponsaBundle\Entity\EqTemplates" table="eq_templates">
    <id name="templateId" type="integer" column="template_id">
      <generator strategy="IDENTITY"/>
    </id>
    <field name="templateObjekt" type="text" column="template_objekt" nullable="true"/>
    <field name="templateStatus" type="string" column="template_status" length="200" nullable="true"/>
    <field name="anlassId" type="bigint" column="anlass_id" nullable="false"/>
    <field name="kontaktId" type="bigint" column="kontakt_id" nullable="false"/>
  </entity>
</doctrine-mapping>
